{





	"待分类": {





		"Axebro_PastelStyle_v2": "<lora:Axebro_PastelStyle_v2:1>",
		"BAS-RELIEF": "<lora:BAS-RELIEF:1>",
		"Candyland-10": "<lora:Candyland-10:1>",
		"CGcutegirlsasw": "<lora:CGcutegirlsasw:1>",
		"CGgamebuilding+dsw": "<lora:CGgamebuilding+dsw:1>",
		"CGgameminicitybsw": "<lora:CGgameminicitybsw:1>",
		"CGproduct asw_v1": "<lora:CGproduct asw_v1:1>",
		"cheongsam_art": "<lora:cheongsam_art:1>",


		"Destijl": "<lora:Destijl:1>",
		"Dream": "<lora:Dream:1>",
		"Dreamwave v2L": "<lora:Dreamwave v2L:1>",
		"epi_noiseoffset2": "<lora:epi_noiseoffset2:1>",
		"FF14CharArt": "<lora:FF14CharArt:1>",
		"FilmVelvia3": "<lora:FilmVelvia3:1>",
		"Fishnets": "<lora:Fishnets:1>",
		"flat_illustration": "<lora:flat_illustration:1>",
		"floating_on_water": "<lora:floating_on_water:1>",
		"flower_lyriel": "<lora:flower_lyriel:1>",
		"Freehand_Brushwork": "<lora:Freehand_Brushwork:1>",
		"fugu": "<lora:fugu:1>",
		"GameIconResearch_currency3_Lora": "<lora:GameIconResearch_currency3_Lora:1>",
		"GameIconResearch_TOY_Lora": "<lora:GameIconResearch_TOY_Lora:1>",
		"Girls'_Frontline-Grig緹__(With_multires_noise_version)": "<lora:Girls'_Frontline-Grig緹__(With_multires_noise_version):1>",

		"gstamp_02-000008": "<lora:gstamp_02-000008:1>",

		"holov7": "<lora:holov7:1>",
		"horikyouko- v1.0": "<lora:horikyouko- v1.0:1>",
		"HouseBlurprint_v1": "<lora:HouseBlurprint_v1:1>",
		"IcfgirlLora_v40": "<lora:IcfgirlLora_v40:1>",
		"icons": "<lora:icons:1>",
		"infirmary_v0.1": "<lora:infirmary_v0.1:1>",
		"Ink scenery": "<lora:Ink scenery:1>",
		"InstantPhotoX3": "<lora:InstantPhotoX3:1>",
		"Isometric_Chinese_style_architecture_v1": "<lora:Isometric_Chinese_style_architecture_v1:1>",
		"IvoryGoldAIv2": "<lora:IvoryGoldAIv2:1>",


		"mechanical_wings-000007": "<lora:mechanical_wings-000007:1>",
		"miaoLan_165": "<lora:miaoLan_165:1>",

		"jwy___v1": "<lora:jwy___v1:1>",
		"kama_v4": "<lora:kama_v4:1>",
		"KATON": "<lora:KATON:1>",
		"kp": "<lora:kp:1>",
		"landingPage_V4": "<lora:landingPage_V4:1>",
		"legver": "<lora:legver:1>",
		"libbg_v16": "<lora:libbg_v16:1>",
		"linebaby": "<lora:linebaby:1>",
		"linglongV1": "<lora:linglongV1:1>",



		"long-000020": "<lora:long-000020:1>",
		"lustermix_v20Safetensor": "<lora:lustermix_v20Safetensor:1>",
		"makina69_karina_v2.1": "<lora:makina69_karina_v2.1:1>",
		"markerhandsketch-V1": "<lora:markerhandsketch-V1:1>",
		"mathayom22": "<lora:mathayom22:1>",
		"midjourney_20230624181825": "<lora:midjourney_20230624181825:1>",
		"mini sence-000008": "<lora:mini sence-000008:1>",
		"miniature_V1": "<lora:miniature_V1:1>",
		"Missile_surfing_v2": "<lora:Missile_surfing_v2:1>",
		"mizuki-nvwls-v1-final": "<lora:mizuki-nvwls-v1-final:1>",
		"Mr_Mc_BokK_V1": "<lora:Mr_Mc_BokK_V1:1>",
		"naked_towel_v0.1": "<lora:naked_towel_v0.1:1>",
		"neowrsk_v2": "<lora:neowrsk_v2:1>",

		"n_2b-10": "<lora:n_2b-10:1>",
		"peeking_out_upper_body_pruned": "<lora:peeking_out_upper_body_pruned:1>",
		"pensketch_lora_v2.3": "<lora:pensketch_lora_v2.3:1>",
		"Perfume_Bottle_v1": "<lora:Perfume_Bottle_v1:1>",
		"poodlepunk": "<lora:poodlepunk:1>",
		"popupparade-10": "<lora:popupparade-10:1>",
		"punishingGreyRaven_V20": "<lora:punishingGreyRaven_V20:1>",
		"quan_style_v2": "<lora:quan_style_v2:1>",
		"Rack-ClayMaterial": "<lora:Rack-ClayMaterial:1>",
		"raidenShogunRealistic_raidenshogun": "<lora:raidenShogunRealistic_raidenshogun:1>",
		"reelmech1v2": "<lora:reelmech1v2:1>",
		"Rosseta": "<lora:Rosseta:1>",

		"shitu-mecha_shitu-mechaV1": "<lora:shitu-mecha_shitu-mechaV1:1>",
		"SidelessLeotard": "<lora:SidelessLeotard:1>",
		"small_scene_V2": "<lora:small_scene_V2:1>",
		"smokeanywhere": "<lora:smokeanywhere:1>",
		"song2": "<lora:song2:1>",
		"soviet-poster": "<lora:soviet-poster:1>",
		"stainglasses": "<lora:stainglasses:1>",
		"styleJelly_v10": "<lora:styleJelly_v10:1>",
		"stylized_3dcg_v4-epoch-000012": "<lora:stylized_3dcg_v4-epoch-000012:1>",
		"Super female mech-V4": "<lora:Super female mech-V4:1>",
		"sweetLolita_v10": "<lora:sweetLolita_v10:1>",
		"takagi-san": "<lora:takagi-san:1>",
		"tattoo_lora01": "<lora:tattoo_lora01:1>",
		"tianfeng_filmgirls5": "<lora:tianfeng_filmgirls5:1>",
		"toon2": "<lora:toon2:1>",
		"Transparent+style_1.0": "<lora:Transparent+style_1.0:1>",
		"underwater": "<lora:underwater:1>",
		"vision_pro_v2": "<lora:vision_pro_v2:1>",
		"waccaLiz-000100": "<lora:waccaLiz-000100:1>",
		"warhammer40000AddonFor_wh40k": "<lora:warhammer40000AddonFor_wh40k:1>",
		"WaterRealflow": "<lora:WaterRealflow:1>",
		"wedding_princess": "<lora:wedding_princess:1>",
		"WipeBack": "<lora:WipeBack:1>",
		"wlop_offset": "<lora:wlop_offset:1>",
		"wowifierV3": "<lora:wowifierV3:1>",
		"wuxia2": "<lora:wuxia2:1>",
		"wyycaimocolorfulink-000009": "<lora:wyycaimocolorfulink-000009:1>"


	},

	"效果和服饰": {
		"add_brightness": "<lora:add_brightness:1>",
		"add_detail": "<lora:add_detail:1>",

		"more_details": "<lora:more_details:1>",

		"background_V2": "<lora:background_V2:1>",
		"oversizedShirt_v10": "<lora:oversizedShirt_v10:1>",
		"princess_carry_v0.1": "<lora:princess_carry_v0.1:1>",
		"shirtTugPoseLORA_shirtTug": "<lora:shirtTugPoseLORA_shirtTug:1>",
		"Tshirt_design": "<lora:Tshirt_design:1>",

		"detailed_eye-10": "<lora:detailed_eye-10:1>",
		"Clothing+-": "<lora:Clothing+-:1>",
		"40d_grey_pantyhose": "<lora:40d_grey_pantyhose:1>",
		"hugeAssAndBoobs_v1": "<lora:hugeAssAndBoobs_v1:1>",

		"bubbledrip": "<lora:bubbledrip:1>",
		"Fire_VFX-000010": "<lora:Fire_VFX-000010:1>",
		


	},


	"2.5D": {

		"1990": "<lora:1990:1>",
		"2.5D _ DAZ风格_v1.0": "<lora:2.5D _ DAZ风格_v1.0:1>",
		"AKchibi": "<lora:AKchibi:1>",
		"blindbox_大概是盲盒_blindbox_v1_mix": "<lora:blindbox_大概是盲盒_blindbox_v1_mix:1>",
		"chibi-v1": "<lora:chibi-v1:1>",
		"chibi_01": "<lora:chibi_01:1>",
		"QINGTOU": "<lora:QINGTOU:1>"


	},




	"三坑+武侠-敦煌": {


		"永劫无间【宁红夜】武侠风_1.0": "<lora:永劫无间【宁红夜】武侠风_1.0:1>",
		"汉服唐风_v3.2": "<lora:汉服唐风_v3.2:1>",

		"武侠 V2_2.0": "<lora:武侠 V2_2.0:1>",
		"hanfudoll_v1.0-000001": "<lora:hanfudoll_v1.0-000001:1>",
		"hanfuMing_v31": "<lora:hanfuMing_v31:1>",
		"hanfuSong_v35": "<lora:hanfuSong_v35:1>",
		"hanfuTang_v35": "<lora:hanfuTang_v35:1>",
		"hanfu_v30": "<lora:hanfu_v30:1>",
		"Chinese_style_20230607154437-000017": "<lora:Chinese_style_20230607154437-000017:1>",
		"cyberhanfu_v1": "<lora:cyberhanfu_v1:1>",
		"jk_lure_dress2": "<lora:jk_lure_dress2:1>",
		"JK制服_v1.0": "<lora:JK制服_v1.0:1>",
		"new_weijin_hanfu": "<lora:new_weijin_hanfu:1>",

		"白昼夜影之国-000002": "<lora:白昼夜影之国-000002:1>"

	},


	"素描和绘画等": {

		"animeoutlineV4_16": "<lora:animeoutlineV4_16:1>",
		"Colorwater_v4": "<lora:Colorwater_v4:1>",
		"剪纸papercut": "<lora:剪纸papercut:1>",

		"minimal vector style": "<lora:minimal vector style:1>",
		"handdraw": "<lora:handdraw:1>",
		"ShanShuiHua_v16": "<lora:ShanShuiHua_v16:1>",

		"ankymoore-04": "<lora:ankymoore-04:1>"

	},

	"动物": {


		"c4ttitudeflexver": "<lora:c4ttitudeflexver:1>",
		"ChineseDragon_v2": "<lora:ChineseDragon_v2:1>",
		"圆滚滚的小动物_Chubby Animals V1.0_V1.0": "<lora:圆滚滚的小动物_Chubby Animals V1.0_V1.0:1>",
		"dog_20230627135046-000018": "<lora:dog_20230627135046-000018:1>"
	},



	"场景,建筑": {


		"locker_room_v0.1": "<lora:locker_room_v0.1:1>",
		"school_outdoors_v0.2": "<lora:school_outdoors_v0.2:1>",
		"school_rooftop_v0.1": "<lora:school_rooftop_v0.1:1>",
		"school_yard_v0.1": "<lora:school_yard_v0.1:1>",

		"首发推荐 _ MG_宠物之家_V1.0": "<lora:首发推荐 _ MG_宠物之家_V1.0:1>",
		"首发推荐 _ 彩色建筑手稿 CHAS_v1": "<lora:首发推荐 _ 彩色建筑手稿 CHAS_v1:1>",
		"建筑测试模型V6_V6": "<lora:建筑测试模型V6_V6:1>",
		"室内设计：极简_宅寂_北欧_Mr_MC_HomeV1": "<lora:室内设计：极简_宅寂_北欧_Mr_MC_HomeV1:1>",


		"XSarchitectural-6Modern small building_xsarchitectural-6": "<lora:XSarchitectural-6Modern small building_xsarchitectural-6:1>",
		"XSarchitectural-8japanwabisabi_xsarchitectural-8japanwabisabi": "<lora:XSarchitectural-8japanwabisabi_xsarchitectural-8japanwabisabi:1>"


	},




	"动漫": {

		"2DspriteV2": "<lora:2DspriteV2:1>",
		"amberGenshinImpact_flexibleV1": "<lora:amberGenshinImpact_flexibleV1:1>",
		"Cartoon cute sticker effect（卡通Q版贴纸效果）LoRa_v1.0": "<lora:Cartoon cute sticker effect（卡通Q版贴纸效果）LoRa_v1.0:1>",
		"Cartoon_cute_sticker_v1": "<lora:Cartoon_cute_sticker_v1:1>",
		"animetarotV51": "<lora:animetarotV51:1>",
		"arknightsTexasThe_v10": "<lora:arknightsTexasThe_v10:1>",
		"ArinaMakihara": "<lora:ArinaMakihara:1>",
		"faruzanGenshinImpact_v10": "<lora:faruzanGenshinImpact_v10:1>",

		"elsa_of_arendelle_v1": "<lora:elsa_of_arendelle_v1:1>",
		"niji-kawayi": "<lora:niji-kawayi:1>",
		"niji-watercolor02": "<lora:niji-watercolor02:1>",
		"nijiarmor_v2": "<lora:nijiarmor_v2:1>",
		"Nijicute": "<lora:Nijicute:1>",
		"nijiDesigner_BlindBox": "<lora:nijiDesigner_BlindBox:1>",
		"NijiEmotes-10": "<lora:NijiEmotes-10:1>",
		"NijiExpressive_V2_v1.0": "<lora:NijiExpressive_V2_v1.0:1>",
		"NijiExpressV2": "<lora:NijiExpressV2:1>",
		"nijifusion": "<lora:nijifusion:1>",
		"nijijourney_1unetonly": "<lora:nijijourney_1unetonly:1>",
		"nijiLOGO": "<lora:nijiLOGO:1>",
		"nijiMecha": "<lora:nijiMecha:1>",
		"nijisharpie": "<lora:nijisharpie:1>",
		"Nijiv5.1style": "<lora:Nijiv5.1style:1>",
		"nijiV5Furry": "<lora:nijiV5Furry:1>",
		"niji_vn_bg": "<lora:niji_vn_bg:1>",
		"JinxLol": "<lora:JinxLol:1>",
		"harunoSakura_v11": "<lora:harunoSakura_v11:1>",
		"KomeijiKoishi": "<lora:KomeijiKoishi:1>",
		"[原创首发] Q版角色-- niji风格卡哇伊_v1.0": "<lora:[原创首发] Q版角色-- niji风格卡哇伊_v1.0:1>",
		"yurikiss": "<lora:yurikiss:1>",
		"yushui": "<lora:yushui:1>",
		"zerosuit-nvwls-v1-final": "<lora:zerosuit-nvwls-v1-final:1>",
		"zyd232_InkStyle_v1_0": "<lora:zyd232_InkStyle_v1_0:1>",
		"[LoCon_LoRA]_Mikan蜜柑_Style": "<lora:[LoCon_LoRA]_Mikan蜜柑_Style:1>",
		"sailor_mars_v1": "<lora:sailor_mars_v1:1>",
		"sailor_venus_v2": "<lora:sailor_venus_v2:1>",
		"yaeMikoRealistic_yaemikoMixed": "<lora:yaeMikoRealistic_yaemikoMixed:1>",
		"yamazakiAn-000125": "<lora:yamazakiAn-000125:1>",

		"YKHB-000000": "<lora:YKHB-000000:1>",

		"[LoRa] Artoria pendragon (swimsuit ruler) FGO  Clothing (With multires noise version) (1)": "<lora:[LoRa] Artori Apendragon (swimsuit ruler) FGO Clothing (With multires noise version) (1):1>",
		"[LoRa] Sword Maiden-Goblin Slayer! Clothing (With multires noise version)": "<lora:[LoRa] Sword Maiden-Goblin Slayer! Clothing (With multires noise version):1>",


		"aquaKonosubaLora_1": "<lora:aquaKonosubaLora_1:1>",
		"ARWSweetLolita": "<lora:ARWSweetLolita:1>"

	},






	"写实": {


		"Realistic+Girl-000016": "<lora:Realistic+Girl-000016:1>",

		"pupu2（大眼萌妹）": "<lora:pupu2（大眼萌妹）:1>",
		"pureInnocentGirl_v25": "<lora:pureInnocentGirl_v25:1>",
		"capricornus 死去的回忆开始攻击我了_V10": "<lora:capricornus 死去的回忆开始攻击我了_V10:1>",
		"BeautyNwsjMajic2-01": "<lora:BeautyNwsjMajic2-01:1>",
		"3DMM_V12": "<lora:3DMM_V12:1>",
		"3DMM_V7": "<lora:3DMM_V7:1>",
		"chineseCosplayerXiaorouseeu_v10": "<lora:chineseCosplayerXiaorouseeu_v10:1>",
		"CyberPunkAI": "<lora:CyberPunkAI:1>",
		"dunhuang2-000004": "<lora:dunhuang2-000004:1>",
		"dunhuangstyle V2.1_v2.1": "<lora:dunhuangstyle V2.1_v2.1:1>",
		"Elegant_hanfu_ruqun_style": "<lora:Elegant_hanfu_ruqun_style:1>",
		"fashigirl-v5.5-lora-naivae-64dim": "<lora:fashigirl-v5.5-lora-naivae-64dim:1>",
		"GPTS4 dreamwave full_478773": "<lora:GPTS4 dreamwave full_478773:1>",

		"GirlfriendMix2": "<lora:GirlfriendMix2:1>",
		"GirlfriendMix_v1_v20": "<lora:GirlfriendMix_v1_v20:1>",

		"breasts_smother_v0.1": "<lora:breasts_smother_v0.1:1>",
		"103423215": "<lora:103423215:1>",
		"hipoly_3dcg_v7-epoch-000012": "<lora:hipoly_3dcg_v7-epoch-000012:1>",
		"concept_x-arms-10": "<lora:concept_x-arms-10:1>",
		"android_18_v110": "<lora:android_18_v110:1>",


		"PMS_v001_4": "<lora:PMS_v001_4:1>",

		"NewChineseStyleSuit_v1": "<lora:NewChineseStyleSuit_v1:1>",
		"little_black_dress_v1.1": "<lora:little_black_dress_v1.1:1>",
		"LeoCyberX": "<lora:LeoCyberX:1>",
		"leolux": "<lora:leolux:1>",
		"koreanDollLikeness_v15": "<lora:koreanDollLikeness_v15:1>",
		"Lemon Summer": "<lora:Lemon Summer:1>",
		"lucyCyberpunk_35Epochs": "<lora:lucyCyberpunk_35Epochs:1>",
		"lucyfleming-07": "<lora:lucyfleming-07:1>",
		"LunarPunkAI": "<lora:LunarPunkAI:1>",
		"【麻瓜lora】nightclub": "<lora:【麻瓜lora】nightclub:1>",
		"【麻瓜lora】副驾驶女友_codriver_v1.0": "<lora:【麻瓜lora】副驾驶女友_codriver_v1.0:1>",
		"【麻瓜lora】真实试衣间自拍_fittingroom_v1": "<lora:【麻瓜lora】真实试衣间自拍_fittingroom_v1:1>",
		"全网首发潮玩_designer toy_v1.0": "<lora:全网首发潮玩_designer toy_v1.0:1>",
		"全网首发｜柔轻羽几何构线 Gentle cubism - Light_Heavy_v1.0": "<lora:全网首发｜柔轻羽几何构线 Gentle cubism - Light_Heavy_v1.0:1>",

		"xiaotuntunshu_v1": "<lora:xiaotuntunshu_v1:0.4>",

		"少女感-shojovibe_v11": "<lora:少女感-shojovibe_v11:1>",
		"彩虹糖_RainbowLOVE_RainbowLight v1.0": "<lora:彩虹糖_RainbowLOVE_RainbowLight v1.0:1>",
		"最新入驻 _ FilmGirl 胶片风 LoRA--全新VELVIA版本_2.0": "<lora:最新入驻 _ FilmGirl 胶片风 LoRA--全新VELVIA版本_2.0:1>",
		"机械风暴丨MG_jixie_v1.0": "<lora:机械风暴丨MG_jixie_v1.0:1>",
		"水墨shuimomix-v4_V4.0": "<lora:水墨shuimomix-v4_V4.0:1>",


		"神里绫华": "<lora:神里绫华:1>",
		"科幻Q版机甲少年_v1.0": "<lora:科幻Q版机甲少年_v1.0:1>",
		"花开绘百世": "<lora:花开绘百世:1>",
		"触发词：clouds PAseerCloudV1": "<lora:触发词：clouds PAseerCloudV1:1>",
		"触发词：ink splash mo": "<lora:触发词：ink splash mo:1>",
		"tpqy": "<lora:tpqy:1>",
		"Yan2": "<lora:Yan2:1>"




	}





}